bravado_asyncio/__init__.py
bravado_asyncio/definitions.py
bravado_asyncio/future_adapter.py
bravado_asyncio/http_client.py
bravado_asyncio/response_adapter.py
bravado_asyncio/thread_loop.py
bravado_asyncio-2.0.2.dist-info/LICENSE.txt
bravado_asyncio-2.0.2.dist-info/METADATA
bravado_asyncio-2.0.2.dist-info/WHEEL
bravado_asyncio-2.0.2.dist-info/top_level.txt
bravado_asyncio-2.0.2.dist-info/RECORD
