Metadata-Version: 2.1
Name: bravado-asyncio
Version: 2.0.2
Summary: asyncio powered HTTP client for bravado
Home-page: https://github.com/sjaensch/bravado-asyncio
Author: Stephan Jaensch
Author-email: sj@sjaensch.org
License: BSD 3-Clause License
Classifier: Development Status :: 5 - Production/Stable
Classifier: Intended Audience :: Developers
Classifier: Topic :: Software Development :: Libraries :: Python Modules
Classifier: License :: OSI Approved :: BSD License
Classifier: Operating System :: OS Independent
Classifier: Programming Language :: Python :: 3.6
Classifier: Programming Language :: Python :: 3.7
Classifier: Programming Language :: Python :: 3.8
Requires-Python: >=3.6
License-File: LICENSE.txt
Requires-Dist: aiohttp (>=3.3)
Requires-Dist: bravado (>=11.0.0)
Requires-Dist: yelp-bytes
Provides-Extra: aiobravado
Requires-Dist: aiobravado ; extra == 'aiobravado'
Provides-Extra: aiohttp_extras
Requires-Dist: aiodns ; extra == 'aiohttp_extras'
Requires-Dist: cchardet ; extra == 'aiohttp_extras'
